example_publish_pypi_medium/__init__.py
example_publish_pypi_medium/example/__init__.py
example_publish_pypi_medium/example/custom_sklearn.py
example_publish_pypi_mediumaaafff-0.6.dist-info/METADATA
example_publish_pypi_mediumaaafff-0.6.dist-info/WHEEL
example_publish_pypi_mediumaaafff-0.6.dist-info/top_level.txt
example_publish_pypi_mediumaaafff-0.6.dist-info/RECORD
